setup.cfg
setup.py
cltool/__init__.py
cltool.egg-info/PKG-INFO
cltool.egg-info/SOURCES.txt
cltool.egg-info/dependency_links.txt
cltool.egg-info/entry_points.txt
cltool.egg-info/not-zip-safe
cltool.egg-info/top_level.txt
scripts/cltool1
scripts/cltool2