Metadata-Version: 1.0
Name: cltool
Version: 0.8.1.3dev
Summary: Example of installing a comand line tool via pip/easy_install
Home-page: https://github.com/farmckon/cltool#cltool
Author: Far McKon
Author-email: FarMcKon@gmail.com
License: UNKNOWN
Platform: UNKNOWN
